{
	"name": "MergedInvoice_UseCase3",
	"properties": {
		"type": "MappingDataFlow",
		"typeProperties": {
			"sources": [
				{
					"dataset": {
						"referenceName": "NewTest",
						"type": "DatasetReference"
					},
					"name": "DOF"
				},
				{
					"dataset": {
						"referenceName": "PW1XX",
						"type": "DatasetReference"
					},
					"name": "PW1XX"
				},
				{
					"dataset": {
						"referenceName": "PW127",
						"type": "DatasetReference"
					},
					"name": "PW127"
				},
				{
					"dataset": {
						"referenceName": "PW150",
						"type": "DatasetReference"
					},
					"name": "PW150"
				},
				{
					"dataset": {
						"referenceName": "TFAN",
						"type": "DatasetReference"
					},
					"name": "TFAN"
				}
			],
			"sinks": [
				{
					"dataset": {
						"referenceName": "Parquet1",
						"type": "DatasetReference"
					},
					"name": "sink1"
				}
			],
			"transformations": [
				{
					"name": "MergedInvoiceUseCase3"
				}
			],
			"scriptLines": [
				"source(output(",
				"          InvoiceFrontPageId as string,",
				"          EngineModel as string,",
				"          SalesOrderNumber as string,",
				"          OtherDocuments as string,",
				"          SDPlant as string,",
				"          PricingDate as date,",
				"          PrimaryModuleType as string,",
				"          PrimaryModule2Type as string,",
				"          SecondaryModuleType as string,",
				"          PrimaryModuleSerialNumber as string,",
				"          PrimaryModule2SerialNumber as string,",
				"          SecondaryModuleSerialNumber as string,",
				"          ReasonForRemovalBW as string,",
				"          ReasonForRemovalAdditionalInfo as string,",
				"          ShopEventDate as date,",
				"          ShippedDate as date,",
				"          InvoiceDate as date,",
				"          InvoiceMonth as string,",
				"          InvoiceNumber as string,",
				"          ShipToCountry as string,",
				"          EndCustomer as string,",
				"          GeographicRegionOfEndCustomer as string,",
				"          PayerAorB as string,",
				"          PrimaryModuleWorkscope as string,",
				"          PrimaryModule2Workscope as string,",
				"          SecondaryModuleWorkscope as string,",
				"          PrimaryModuleTSN as double,",
				"          PrimaryModuleCSN as double,",
				"          PrimaryModuleTSO as double,",
				"          PrimaryModuleCSO as double,",
				"          PrimaryModuleTSHSI as double,",
				"          PrimaryModuleTSLV as double,",
				"          PrimaryModule2TSN as double,",
				"          PrimaryModule2CSN as double,",
				"          PrimaryModule2TSO as double,",
				"          PrimaryModule2CSO as double,",
				"          PrimaryModule2TSHSI as double,",
				"          PrimaryModule2TSLV as double,",
				"          SecondaryModuleTSN as double,",
				"          SecondaryModuleCSN as double,",
				"          SecondaryModuleTSO as double,",
				"          SecondaryModuleCSO as double,",
				"          SecondaryModuleTSHSI as double,",
				"          SecondaryModuleTSLV as double,",
				"          PrimaryModuleWorkscopeFinal as string,",
				"          PrimaryModule2WorkscopeFinal as string,",
				"          SecondaryModuleWorkscopeFinal as string,",
				"          HSICategory as string,",
				"          TargetHSIInterval as double,",
				"          PrimaryModuleOVHCategory as string,",
				"          PrimaryModuleTargetTBO as double,",
				"          PrimaryModule2OVHCategory as double,",
				"          PrimaryModule2TargetTBO as double,",
				"          SecondaryModuleOVHCategory as string,",
				"          SecondaryModuleTargetTBO as double,",
				"          PreviousEventHistory as string",
				"     ),",
				"     allowSchemaDrift: true,",
				"     validateSchema: false,",
				"     ignoreNoFilesFound: false) ~> DOF",
				"source(output(",
				"          InvoiceFrontPageId as string,",
				"          EngineModel as string,",
				"          SalesOrderNumber as string,",
				"          OtherDocuments as string,",
				"          SDPlant as string,",
				"          PricingDate as date,",
				"          PrimaryModuleType as string,",
				"          PrimaryModule2Type as string,",
				"          SecondaryModuleType as string,",
				"          PrimaryModuleSerialNumber as string,",
				"          PrimaryModule2SerialNumber as string,",
				"          SecondaryModuleSerialNumber as string,",
				"          ReasonForRemovalBW as string,",
				"          ReasonForRemovalAdditionalInfo as string,",
				"          ShopEventDate as date,",
				"          ShippedDate as date,",
				"          InvoiceDate as date,",
				"          InvoiceMonth as string,",
				"          InvoiceNumber as string,",
				"          ShipToCountry as string,",
				"          EndCustomer as string,",
				"          GeographicRegionOfEndCustomer as string,",
				"          PayerAorB as string,",
				"          PrimaryModuleWorkscope as string,",
				"          PrimaryModule2Workscope as string,",
				"          SecondaryModuleWorkscope as string,",
				"          PrimaryModuleTSN as float,",
				"          PrimaryModuleCSN as float,",
				"          PrimaryModuleTSO as float,",
				"          PrimaryModuleCSO as float,",
				"          PrimaryModuleTSHSI as float,",
				"          PrimaryModuleTSLV as float,",
				"          PrimaryModule2TSN as float,",
				"          PrimaryModule2CSN as float,",
				"          PrimaryModule2TSO as float,",
				"          PrimaryModule2CSO as float,",
				"          PrimaryModule2TSHSI as float,",
				"          PrimaryModule2TSLV as float,",
				"          SecondaryModuleTSN as float,",
				"          SecondaryModuleCSN as float,",
				"          SecondaryModuleTSO as float,",
				"          SecondaryModuleCSO as float,",
				"          SecondaryModuleTSHSI as float,",
				"          SecondaryModuleTSLV as float,",
				"          PrimaryModuleWorkscopeFinal as string,",
				"          PrimaryModule2WorkscopeFinal as string,",
				"          SecondaryModuleWorkscopeFinal as string,",
				"          HSICategory as string,",
				"          TargetHSIInterval as float,",
				"          PrimaryModuleOVHCategory as string,",
				"          PrimaryModuleTargetTBO as float,",
				"          PrimaryModule2OVHCategory as float,",
				"          PrimaryModule2TargetTBO as float,",
				"          SecondaryModuleOVHCategory as string,",
				"          SecondaryModuleTargetTBO as float,",
				"          PreviousEventHistory as string",
				"     ),",
				"     allowSchemaDrift: true,",
				"     validateSchema: false,",
				"     ignoreNoFilesFound: false) ~> PW1XX",
				"source(output(",
				"          InvoiceFrontPageId as string,",
				"          EngineModel as string,",
				"          SalesOrderNumber as string,",
				"          OtherDocuments as string,",
				"          SDPlant as string,",
				"          PricingDate as date,",
				"          PrimaryModuleType as string,",
				"          PrimaryModule2Type as string,",
				"          SecondaryModuleType as string,",
				"          PrimaryModuleSerialNumber as string,",
				"          PrimaryModule2SerialNumber as string,",
				"          SecondaryModuleSerialNumber as string,",
				"          ReasonForRemovalBW as string,",
				"          ReasonForRemovalAdditionalInfo as string,",
				"          ShopEventDate as date,",
				"          ShippedDate as date,",
				"          InvoiceDate as date,",
				"          InvoiceMonth as string,",
				"          InvoiceNumber as string,",
				"          ShipToCountry as string,",
				"          EndCustomer as string,",
				"          GeographicRegionOfEndCustomer as string,",
				"          PayerAorB as string,",
				"          PrimaryModuleWorkscope as string,",
				"          PrimaryModule2Workscope as string,",
				"          SecondaryModuleWorkscope as string,",
				"          PrimaryModuleTSN as float,",
				"          PrimaryModuleCSN as float,",
				"          PrimaryModuleTSO as float,",
				"          PrimaryModuleCSO as float,",
				"          PrimaryModuleTSHSI as float,",
				"          PrimaryModuleTSLV as float,",
				"          PrimaryModule2TSN as float,",
				"          PrimaryModule2CSN as float,",
				"          PrimaryModule2TSO as float,",
				"          PrimaryModule2CSO as float,",
				"          PrimaryModule2TSHSI as float,",
				"          PrimaryModule2TSLV as float,",
				"          SecondaryModuleTSN as float,",
				"          SecondaryModuleCSN as float,",
				"          SecondaryModuleTSO as float,",
				"          SecondaryModuleCSO as float,",
				"          SecondaryModuleTSHSI as float,",
				"          SecondaryModuleTSLV as float,",
				"          PrimaryModuleWorkscopeFinal as string,",
				"          PrimaryModule2WorkscopeFinal as string,",
				"          SecondaryModuleWorkscopeFinal as string,",
				"          HSICategory as string,",
				"          TargetHSIInterval as float,",
				"          PrimaryModuleOVHCategory as string,",
				"          PrimaryModuleTargetTBO as float,",
				"          PrimaryModule2OVHCategory as float,",
				"          PrimaryModule2TargetTBO as float,",
				"          SecondaryModuleOVHCategory as string,",
				"          SecondaryModuleTargetTBO as float,",
				"          PreviousEventHistory as string",
				"     ),",
				"     allowSchemaDrift: true,",
				"     validateSchema: false,",
				"     ignoreNoFilesFound: false) ~> PW127",
				"source(output(",
				"          InvoiceFrontPageId as string,",
				"          EngineModel as string,",
				"          SalesOrderNumber as string,",
				"          OtherDocuments as string,",
				"          SDPlant as string,",
				"          PricingDate as date,",
				"          PrimaryModuleType as string,",
				"          PrimaryModule2Type as string,",
				"          SecondaryModuleType as string,",
				"          PrimaryModuleSerialNumber as string,",
				"          PrimaryModule2SerialNumber as string,",
				"          SecondaryModuleSerialNumber as string,",
				"          ReasonForRemovalBW as string,",
				"          ReasonForRemovalAdditionalInfo as string,",
				"          ShopEventDate as date,",
				"          ShippedDate as date,",
				"          InvoiceDate as date,",
				"          InvoiceMonth as string,",
				"          InvoiceNumber as string,",
				"          ShipToCountry as string,",
				"          EndCustomer as string,",
				"          GeographicRegionOfEndCustomer as string,",
				"          PayerAorB as string,",
				"          PrimaryModuleWorkscope as string,",
				"          PrimaryModule2Workscope as string,",
				"          SecondaryModuleWorkscope as string,",
				"          PrimaryModuleTSN as double,",
				"          PrimaryModuleCSN as double,",
				"          PrimaryModuleTSO as double,",
				"          PrimaryModuleCSO as double,",
				"          PrimaryModuleTSHSI as double,",
				"          PrimaryModuleTSLV as double,",
				"          PrimaryModule2TSN as double,",
				"          PrimaryModule2CSN as double,",
				"          PrimaryModule2TSO as double,",
				"          PrimaryModule2CSO as double,",
				"          PrimaryModule2TSHSI as double,",
				"          PrimaryModule2TSLV as double,",
				"          SecondaryModuleTSN as double,",
				"          SecondaryModuleCSN as double,",
				"          SecondaryModuleTSO as double,",
				"          SecondaryModuleCSO as double,",
				"          SecondaryModuleTSHSI as double,",
				"          SecondaryModuleTSLV as double,",
				"          PrimaryModuleWorkscopeFinal as string,",
				"          PrimaryModule2WorkscopeFinal as string,",
				"          SecondaryModuleWorkscopeFinal as string,",
				"          HSICategory as string,",
				"          TargetHSIInterval as double,",
				"          PrimaryModuleOVHCategory as string,",
				"          PrimaryModuleTargetTBO as double,",
				"          PrimaryModule2OVHCategory as double,",
				"          PrimaryModule2TargetTBO as double,",
				"          SecondaryModuleOVHCategory as string,",
				"          SecondaryModuleTargetTBO as double,",
				"          PreviousEventHistory as string",
				"     ),",
				"     allowSchemaDrift: true,",
				"     validateSchema: false,",
				"     ignoreNoFilesFound: false) ~> PW150",
				"source(output(",
				"          InvoiceFrontPageId as string,",
				"          EngineModel as string,",
				"          SalesOrderNumber as string,",
				"          OtherDocuments as string,",
				"          SDPlant as string,",
				"          PricingDate as date,",
				"          PrimaryModuleType as string,",
				"          PrimaryModule2Type as string,",
				"          SecondaryModuleType as string,",
				"          PrimaryModuleSerialNumber as string,",
				"          PrimaryModule2SerialNumber as string,",
				"          SecondaryModuleSerialNumber as string,",
				"          ReasonForRemovalBW as string,",
				"          ReasonForRemovalAdditionalInfo as string,",
				"          ShopEventDate as date,",
				"          ShippedDate as date,",
				"          InvoiceDate as date,",
				"          InvoiceMonth as string,",
				"          InvoiceNumber as string,",
				"          ShipToCountry as string,",
				"          EndCustomer as string,",
				"          GeographicRegionOfEndCustomer as string,",
				"          PayerAorB as string,",
				"          PrimaryModuleWorkscope as string,",
				"          PrimaryModule2Workscope as string,",
				"          SecondaryModuleWorkscope as string,",
				"          PrimaryModuleTSN as double,",
				"          PrimaryModuleCSN as double,",
				"          PrimaryModuleTSO as double,",
				"          PrimaryModuleCSO as double,",
				"          PrimaryModuleTSHSI as double,",
				"          PrimaryModuleTSLV as double,",
				"          PrimaryModule2TSN as double,",
				"          PrimaryModule2CSN as double,",
				"          PrimaryModule2TSO as double,",
				"          PrimaryModule2CSO as double,",
				"          PrimaryModule2TSHSI as double,",
				"          PrimaryModule2TSLV as double,",
				"          SecondaryModuleTSN as double,",
				"          SecondaryModuleCSN as double,",
				"          SecondaryModuleTSO as double,",
				"          SecondaryModuleCSO as double,",
				"          SecondaryModuleTSHSI as double,",
				"          SecondaryModuleTSLV as double,",
				"          PrimaryModuleWorkscopeFinal as string,",
				"          PrimaryModule2WorkscopeFinal as string,",
				"          SecondaryModuleWorkscopeFinal as string,",
				"          HSICategory as string,",
				"          TargetHSIInterval as double,",
				"          PrimaryModuleOVHCategory as string,",
				"          PrimaryModuleTargetTBO as double,",
				"          PrimaryModule2OVHCategory as double,",
				"          PrimaryModule2TargetTBO as double,",
				"          SecondaryModuleOVHCategory as string,",
				"          SecondaryModuleTargetTBO as double,",
				"          PreviousEventHistory as string",
				"     ),",
				"     allowSchemaDrift: true,",
				"     validateSchema: false,",
				"     ignoreNoFilesFound: false) ~> TFAN",
				"DOF, TFAN, PW1XX, PW150, PW127 union(byName: true,",
				"     partitionBy('hash', 1))~> MergedInvoiceUseCase3",
				"MergedInvoiceUseCase3 sink(allowSchemaDrift: true,",
				"     validateSchema: false,",
				"     format: 'parquet',",
				"     partitionFileNames:['MergedInvoice_UseCase3'],",
				"     umask: 0022,",
				"     preCommands: [],",
				"     postCommands: [],",
				"     skipDuplicateMapInputs: true,",
				"     skipDuplicateMapOutputs: true,",
				"     partitionBy('hash', 1)) ~> sink1"
			]
		}
	}
}